<?xml version="1.0" encoding="utf-8"?>
<search>
  
  
  
  <entry>
    <title>Hexo预定义参数</title>
    <link href="/2022/06/29/Hexo%E9%A2%84%E5%AE%9A%E4%B9%89%E5%8F%82%E6%95%B0/"/>
    <url>/2022/06/29/Hexo%E9%A2%84%E5%AE%9A%E4%B9%89%E5%8F%82%E6%95%B0/</url>
    
    <content type="html"><![CDATA[<table><thead><tr><th align="left">参数</th><th align="left">描述</th><th align="left">默认值</th></tr></thead><tbody><tr><td align="left"><code>layout</code></td><td align="left">布局</td><td align="left"><a href="https://hexo.io/zh-cn/docs/configuration#%E6%96%87%E7%AB%A0"><code>config.default_layout</code></a></td></tr><tr><td align="left"><code>title</code></td><td align="left">标题</td><td align="left">文章的文件名</td></tr><tr><td align="left"><code>date</code></td><td align="left">建立日期</td><td align="left">文件建立日期</td></tr><tr><td align="left"><code>updated</code></td><td align="left">更新日期</td><td align="left">文件更新日期</td></tr><tr><td align="left"><code>comments</code></td><td align="left">开启文章的评论功能</td><td align="left">true</td></tr><tr><td align="left"><code>tags</code></td><td align="left">标签（不适用于分页）</td><td align="left"></td></tr><tr><td align="left"><code>categories</code></td><td align="left">分类（不适用于分页）</td><td align="left"></td></tr><tr><td align="left"><code>permalink</code></td><td align="left">覆盖文章网址</td><td align="left"></td></tr><tr><td align="left"><code>excerpt</code></td><td align="left">纯文本的页面摘录 使用 <a href="https://hexo.io/docs/tag-plugins#Post-Excerpt">此插件</a> 来格式化文本</td><td align="left"></td></tr><tr><td align="left"><code>disableNunjucks</code></td><td align="left">启用Nunjucks标签<code>&#123;&#123; &#125;&#125;</code>/<code>&#123;% %&#125;</code>和<a href="https://hexo.io/docs/tag-plugins">标签插件</a>时禁止渲染。</td><td align="left"></td></tr><tr><td align="left"><code>lang</code></td><td align="left">设置语言以覆盖<a href="https://hexo.io/docs/internationalization#Path">自动检测</a></td><td align="left">Inherited from <code>_config.yml</code></td></tr></tbody></table>]]></content>
    
    
    <categories>
      
      <category>CODE</category>
      
    </categories>
    
    
    <tags>
      
      <tag>MarkDown</tag>
      
    </tags>
    
  </entry>
  
  
  
  <entry>
    <title>2022年暑假目标</title>
    <link href="/2022/06/29/2022%E5%B9%B4%E6%9A%91%E5%81%87%E7%9B%AE%E6%A0%87/"/>
    <url>/2022/06/29/2022%E5%B9%B4%E6%9A%91%E5%81%87%E7%9B%AE%E6%A0%87/</url>
    
    <content type="html"><![CDATA[<h1 id="2022年暑假目标"><a href="#2022年暑假目标" class="headerlink" title="2022年暑假目标"></a>2022年暑假目标</h1><p>不知不觉又在这SB学校<strong>混</strong>了一学期。</p><p>今年暑假，我把我的名字改成了“<strong>逆属玄</strong>”。</p><p>这个名字有点怪，但是我实际上希望它的意义是“<strong>逆风局更多属于玄学成分</strong>”。</p><p>希望它能来激励自己。</p><p>今年的几件事压得我喘不过气来，我愈发感觉我变成熟了，但又能感觉到我的迷茫。</p><p>身边的Homie来了又走，<strong>感觉身边没一个人真的懂我</strong>。</p><p>喜欢的女孩子和其他人在一起了，我当<strong>小丑</strong>的事全班还都知道。</p><p>生地考试好不容易熬过去了，现在又得迎接中考的压力。</p><p>暑假玩一个月<strong>傻逼学校</strong>又要非法补课，还得交两千。</p><p>真想给她妈逼干透，这傻逼地方。</p><p>中国的人口就不能鸡巴少点吗，<strong>操你妈</strong>。</p><p>好好想想暑假该干嘛吧，反正也没啥意思。</p><hr><h3 id="CODE"><a href="#CODE" class="headerlink" title="CODE"></a>CODE</h3><ol><li>  学习C语言 EasyX</li><li>  精通Python高级编程 </li><li>  用Pygame做一个有意思的游戏</li><li>  精通C#高级编程</li><li>  多刷点算法题</li><li>  深入WPF</li><li>  学习RUST</li><li>  精通前端 学习Vue.js</li><li>  多做几个DEMO和项目</li><li>  改良自己的博客</li><li>  入门网络攻防</li></ol><p>希望自己学习时能更有耐心 虚心求教.</p><hr><h3 id="学习"><a href="#学习" class="headerlink" title="学习"></a>学习</h3><ol><li>  把傻逼数学成绩提上去</li><li>  把傻逼物理成绩提上去</li><li>  BE HUMBLE.</li></ol><p>不知道为什么 我理科成绩一直不太好 可能是因为我更习惯用右脑思考吧</p><hr><h3 id="杂类"><a href="#杂类" class="headerlink" title="杂类"></a>杂类</h3><ol><li>  过得开心点</li><li>  能多听点<strong>HipHop</strong></li><li>  <strong>头发留长点</strong></li><li>  别无精打采</li><li>  别无所事事</li><li>  别像个NT一样</li><li>  别太在意任何人 包括自己</li></ol><p>知道我博客可能没多少人看 就写着玩吧</p><p>重在情绪</p><p><em><strong><u>Fuck Everything.</u></strong></em></p>]]></content>
    
    
    <categories>
      
      <category>Life</category>
      
    </categories>
    
    
    <tags>
      
      <tag>Me</tag>
      
    </tags>
    
  </entry>
  
  
  
  <entry>
    <title>简洁的文本编辑器eXhale</title>
    <link href="/2022/05/05/%E7%AE%80%E6%B4%81%E7%9A%84%E6%96%87%E6%9C%AC%E7%BC%96%E8%BE%91%E5%99%A8-eXhale-1-5-PLUS%E5%8F%91%E5%B8%83/"/>
    <url>/2022/05/05/%E7%AE%80%E6%B4%81%E7%9A%84%E6%96%87%E6%9C%AC%E7%BC%96%E8%BE%91%E5%99%A8-eXhale-1-5-PLUS%E5%8F%91%E5%B8%83/</url>
    
    <content type="html"><![CDATA[<h1 id="简洁的文本编辑器-eXhale"><a href="#简洁的文本编辑器-eXhale" class="headerlink" title="简洁的文本编辑器 eXhale"></a>简洁的文本编辑器 eXhale</h1><p><img src="/img/eXhale1.5PLUS.png" alt="预览"></p><p>这是我自己构思制作的文本编辑器eXhale Editor。</p><hr><p><strong>特点</strong>：</p><p>为了小和简单而创造，体积仅136KB（需安装 .NET 6.0 Desktop Runtime）</p><p>支持自定义样式</p><p>逻辑简单易于上手</p><p>界面UI简洁</p><hr><p><strong>缺点</strong>：</p><p>功能较少</p><p>使用体验欠缺，需优化</p><hr><p>欢迎使用：</p><p>蓝奏云：<a href="https://akara.lanzoux.com/ig18U073kh4h">https://akara.lanzoux.com/ig18U073kh4h</a> ( 最新版本 1.26 )</p>]]></content>
    
    
    
    <tags>
      
      <tag>软件</tag>
      
    </tags>
    
  </entry>
  
  
  
  <entry>
    <title>MCU时间线 / 观影顺序</title>
    <link href="/2022/05/05/MCU%E6%97%B6%E9%97%B4%E7%BA%BF-%E8%A7%82%E5%BD%B1%E9%A1%BA%E5%BA%8F/"/>
    <url>/2022/05/05/MCU%E6%97%B6%E9%97%B4%E7%BA%BF-%E8%A7%82%E5%BD%B1%E9%A1%BA%E5%BA%8F/</url>
    
    <content type="html"><![CDATA[<h1 id="MCU时间线-观影顺序"><a href="#MCU时间线-观影顺序" class="headerlink" title="MCU时间线 / 观影顺序"></a>MCU时间线 / 观影顺序</h1><p>第一部，《钢铁侠1》<br>第二部，《无敌浩克》<br>第三部，《钢铁侠2》<br>第四部，《雷神》<br>第五部，《美国队长1：复仇者先锋》<br>第六部，《复仇者联盟1》<br>第七部，《钢铁侠3 》<br>第八部，《雷神2:黑暗世界》<br>第九部，《美国队长2:冬日战士》<br>第十部，《银河护卫队》<br>第十一部，《复仇者联盟2:奥创纪元》<br>第十二部，《蚁人》<br>第十三部，《美国队长3:内战》<br>第十四部，《奇异博士》<br>第十五部，《银河护卫队2》<br>第十六部，《蜘蛛侠:英雄归来》<br>第十七部，《雷神3：诸神黄昏》<br>第十八部，《黑豹》<br>第十九部，《复仇者联盟3:无限战争》<br>第二十部，《蚁人2：黄蜂女现身》<br>第二十一部，《惊奇队长》<br>第二十二部，《复仇者联盟4：终局之战》<br>第二十三部，《蜘蛛侠：英雄远征》<br>第二十四部，《黑寡妇》<br>第二十五部，《尚气与十环传奇》<br>第二十六部，《永恒族》<br>第二十七部，《蜘蛛侠：英雄无归》</p>]]></content>
    
    
    
    <tags>
      
      <tag>影视</tag>
      
    </tags>
    
  </entry>
  
  
  
  <entry>
    <title>MD速查文档</title>
    <link href="/2022/01/25/MD%E9%80%9F%E6%9F%A5%E6%96%87%E6%A1%A3/"/>
    <url>/2022/01/25/MD%E9%80%9F%E6%9F%A5%E6%96%87%E6%A1%A3/</url>
    
    <content type="html"><![CDATA[<h1 id="MD速查文档"><a href="#MD速查文档" class="headerlink" title="MD速查文档"></a>MD速查文档</h1><p>[TOC]</p><h2 id="基本语法"><a href="#基本语法" class="headerlink" title="基本语法"></a>基本语法</h2><h3 id="标题（Heading）"><a href="#标题（Heading）" class="headerlink" title="标题（Heading）"></a>标题（Heading）</h3><figure class="highlight markdown"><table><tr><td class="gutter"><pre><span class="line">1</span><br><span class="line">2</span><br><span class="line">3</span><br></pre></td><td class="code"><pre><code class="hljs markdown"><span class="hljs-section"># H1</span><br><span class="hljs-section">## H2</span><br><span class="hljs-section">### H3</span><br></code></pre></td></tr></table></figure><h3 id="加粗（Bold）"><a href="#加粗（Bold）" class="headerlink" title="加粗（Bold）"></a>加粗（Bold）</h3><figure class="highlight markdown"><table><tr><td class="gutter"><pre><span class="line">1</span><br></pre></td><td class="code"><pre><code class="hljs markdown"><span class="hljs-strong">**bold text**</span><br></code></pre></td></tr></table></figure><h3 id="斜体（Italic）"><a href="#斜体（Italic）" class="headerlink" title="斜体（Italic）"></a>斜体（Italic）</h3><figure class="highlight markdown"><table><tr><td class="gutter"><pre><span class="line">1</span><br></pre></td><td class="code"><pre><code class="hljs markdown"><span class="hljs-emphasis">*italicized text*</span><br></code></pre></td></tr></table></figure><h3 id="引用块（Blockquote）"><a href="#引用块（Blockquote）" class="headerlink" title="引用块（Blockquote）"></a>引用块（Blockquote）</h3><figure class="highlight markdown"><table><tr><td class="gutter"><pre><span class="line">1</span><br></pre></td><td class="code"><pre><code class="hljs markdown"><span class="hljs-quote">&gt; This is a blockquote</span><br></code></pre></td></tr></table></figure><h3 id="有序列表-（Ordered-List）"><a href="#有序列表-（Ordered-List）" class="headerlink" title="有序列表 （Ordered List）"></a>有序列表 （Ordered List）</h3><figure class="highlight markdown"><table><tr><td class="gutter"><pre><span class="line">1</span><br><span class="line">2</span><br><span class="line">3</span><br></pre></td><td class="code"><pre><code class="hljs markdown"><span class="hljs-bullet">1.</span> First<br><span class="hljs-bullet">2.</span> Second<br><span class="hljs-bullet">3.</span> Third<br></code></pre></td></tr></table></figure><h3 id="代码（Code）"><a href="#代码（Code）" class="headerlink" title="代码（Code）"></a>代码（Code）</h3><figure class="highlight markdown"><table><tr><td class="gutter"><pre><span class="line">1</span><br></pre></td><td class="code"><pre><code class="hljs markdown"><span class="hljs-code">`code`</span><br></code></pre></td></tr></table></figure><h3 id="分隔线（Horizontal-Rule）"><a href="#分隔线（Horizontal-Rule）" class="headerlink" title="分隔线（Horizontal Rule）"></a>分隔线（Horizontal Rule）</h3><figure class="highlight markdown"><table><tr><td class="gutter"><pre><span class="line">1</span><br></pre></td><td class="code"><pre><code class="hljs markdown">---<br></code></pre></td></tr></table></figure><h3 id="链接（Link）"><a href="#链接（Link）" class="headerlink" title="链接（Link）"></a>链接（Link）</h3><figure class="highlight markdown"><table><tr><td class="gutter"><pre><span class="line">1</span><br></pre></td><td class="code"><pre><code class="hljs markdown">[<span class="hljs-string">title</span>](<span class="hljs-link">https://www.example.com</span>)<br></code></pre></td></tr></table></figure><h3 id="图片（Image）"><a href="#图片（Image）" class="headerlink" title="图片（Image）"></a>图片（Image）</h3><figure class="highlight markdown"><table><tr><td class="gutter"><pre><span class="line">1</span><br></pre></td><td class="code"><pre><code class="hljs markdown">![<span class="hljs-string">alt text</span>](<span class="hljs-link">image.png</span>)<br></code></pre></td></tr></table></figure><h2 id="扩展语法"><a href="#扩展语法" class="headerlink" title="扩展语法"></a>扩展语法</h2><h3 id="表格（Table）"><a href="#表格（Table）" class="headerlink" title="表格（Table）"></a>表格（Table）</h3><figure class="highlight markdown"><table><tr><td class="gutter"><pre><span class="line">1</span><br><span class="line">2</span><br><span class="line">3</span><br><span class="line">4</span><br></pre></td><td class="code"><pre><code class="hljs markdown">| Syntax      | Description |<br>| ----------- | ----------- |<br>| Header      | Title       |<br>| Paragraph   | Text        |<br></code></pre></td></tr></table></figure><table><thead><tr><th>Syntax</th><th>Description</th></tr></thead><tbody><tr><td>Header</td><td>Title</td></tr><tr><td>Paragraph</td><td>Text</td></tr></tbody></table><h3 id="代码块-（Fenced-Code-Block）"><a href="#代码块-（Fenced-Code-Block）" class="headerlink" title="代码块 （Fenced Code Block）"></a>代码块 （Fenced Code Block）</h3><figure class="highlight c"><table><tr><td class="gutter"><pre><span class="line">1</span><br><span class="line">2</span><br><span class="line">3</span><br><span class="line">4</span><br><span class="line">5</span><br><span class="line">6</span><br><span class="line">7</span><br><span class="line">8</span><br><span class="line">9</span><br><span class="line">10</span><br><span class="line">11</span><br></pre></td><td class="code"><pre><code class="hljs c">```<br><span class="hljs-meta">#<span class="hljs-meta-keyword">include</span> <span class="hljs-meta-string">&lt;stdio.h&gt;</span></span><br><br><span class="hljs-function"><span class="hljs-keyword">int</span> <span class="hljs-title">main</span><span class="hljs-params">()</span></span><br><span class="hljs-function"></span>&#123;<br><span class="hljs-keyword">char</span> Hello[] = <span class="hljs-string">&quot;Hello World!&quot;</span>;<br><br><span class="hljs-built_in">printf</span>(<span class="hljs-string">&quot;%s&quot;</span>, Hello);<br><br><span class="hljs-keyword">return</span> <span class="hljs-number">0</span>;<br>&#125;<br></code></pre></td></tr></table></figure><h3 id="脚注（Footnote）"><a href="#脚注（Footnote）" class="headerlink" title="脚注（Footnote）"></a>脚注（Footnote）</h3><figure class="highlight markdown"><table><tr><td class="gutter"><pre><span class="line">1</span><br><span class="line">2</span><br></pre></td><td class="code"><pre><code class="hljs markdown">Here&#x27;s a sentence with a footnote. [^1]<br>[<span class="hljs-symbol">^1</span>]: <span class="hljs-link">This is the footnote.</span><br></code></pre></td></tr></table></figure><h3 id="标题编号（Heading-ID）"><a href="#标题编号（Heading-ID）" class="headerlink" title="标题编号（Heading ID）"></a>标题编号（Heading ID）</h3><figure class="highlight markdown"><table><tr><td class="gutter"><pre><span class="line">1</span><br></pre></td><td class="code"><pre><code class="hljs markdown"><span class="hljs-section">### My Great Heading &#123;#custom-id&#125;</span><br></code></pre></td></tr></table></figure><h3 id="定义列表（Definition-list）"><a href="#定义列表（Definition-list）" class="headerlink" title="定义列表（Definition list）"></a>定义列表（Definition list）</h3><figure class="highlight markdown"><table><tr><td class="gutter"><pre><span class="line">1</span><br><span class="line">2</span><br></pre></td><td class="code"><pre><code class="hljs markdown">term<br>: definition<br></code></pre></td></tr></table></figure><h3 id="删除线（Strikethrough）"><a href="#删除线（Strikethrough）" class="headerlink" title="删除线（Strikethrough）"></a>删除线（Strikethrough）</h3><figure class="highlight markdown"><table><tr><td class="gutter"><pre><span class="line">1</span><br></pre></td><td class="code"><pre><code class="hljs markdown">~~Delete this~~<br></code></pre></td></tr></table></figure><h3 id="任务列表（Task-List）"><a href="#任务列表（Task-List）" class="headerlink" title="任务列表（Task List）"></a>任务列表（Task List）</h3><figure class="highlight markdown"><table><tr><td class="gutter"><pre><span class="line">1</span><br><span class="line">2</span><br><span class="line">3</span><br></pre></td><td class="code"><pre><code class="hljs markdown"><span class="hljs-bullet">-</span> [x] Write the press release<br><span class="hljs-bullet">-</span> [ ] Update the website<br><span class="hljs-bullet">-</span> [ ] Contact the media<br></code></pre></td></tr></table></figure>]]></content>
    
    
    <categories>
      
      <category>CODE</category>
      
    </categories>
    
    
    <tags>
      
      <tag>MarkDown</tag>
      
    </tags>
    
  </entry>
  
  
  
  <entry>
    <title>Tkinter快速上手</title>
    <link href="/2021/11/01/Tkinter%E5%BF%AB%E9%80%9F%E4%B8%8A%E6%89%8B/"/>
    <url>/2021/11/01/Tkinter%E5%BF%AB%E9%80%9F%E4%B8%8A%E6%89%8B/</url>
    
    <content type="html"><![CDATA[<h1 id="Tkinter快速上手"><a href="#Tkinter快速上手" class="headerlink" title="Tkinter快速上手"></a>Tkinter快速上手</h1><p><em><strong>本文由</strong>Diiz7</em><em>编写，第一次写文档，如有遗漏，欢迎指出  =D</em>**</p><p>2021.10.4 14:08:20</p><h2 id="1-1-Tkinter的简介"><a href="#1-1-Tkinter的简介" class="headerlink" title="1.1 Tkinter的简介"></a>1.1 Tkinter的简介</h2><p> Tkinter 是 Python 内置的标准 GUI 库，可以运行在绝大多数的操作系统上（如Windows, Mac, Linux, Unix）</p><p>下面是一个简单的示例，当你将它编译后，你将会得到一个标题为tk的窗体</p><figure class="highlight python"><table><tr><td class="gutter"><pre><span class="line">1</span><br><span class="line">2</span><br><span class="line">3</span><br><span class="line">4</span><br><span class="line">5</span><br></pre></td><td class="code"><pre><code class="hljs python"><span class="hljs-keyword">from</span> tkinter <span class="hljs-keyword">import</span> *   <span class="hljs-comment">#引用tkinter</span><br><br>mainwindow = Tk()<br><br>mainwindow.mainloop()   <span class="hljs-comment">#使窗体进入信息循环</span><br></code></pre></td></tr></table></figure><p>我们还可以向其中加入一些窗体的属性</p><figure class="highlight python"><table><tr><td class="gutter"><pre><span class="line">1</span><br><span class="line">2</span><br><span class="line">3</span><br><span class="line">4</span><br><span class="line">5</span><br><span class="line">6</span><br><span class="line">7</span><br></pre></td><td class="code"><pre><code class="hljs python"><span class="hljs-keyword">from</span> tkinter <span class="hljs-keyword">import</span> *<br><br>mainwindow = Tk()<br>mainwindow.geometry(<span class="hljs-string">&quot;350x400&quot;</span>)     <span class="hljs-comment">#规定窗体大小</span><br>mainwindow.title(<span class="hljs-string">&quot;Hello World&quot;</span>)    <span class="hljs-comment">#规定窗体标题</span><br><br>mainwindow.mainloop()<br></code></pre></td></tr></table></figure><h2 id="1-2-控件"><a href="#1-2-控件" class="headerlink" title="1.2 控件"></a>1.2 控件</h2><p>Tkinter提供了许多的控件，我们可以选择控件来把它放在窗体上</p><figure class="highlight python"><table><tr><td class="gutter"><pre><span class="line">1</span><br><span class="line">2</span><br><span class="line">3</span><br><span class="line">4</span><br><span class="line">5</span><br><span class="line">6</span><br><span class="line">7</span><br><span class="line">8</span><br><span class="line">9</span><br><span class="line">10</span><br><span class="line">11</span><br><span class="line">12</span><br><span class="line">13</span><br></pre></td><td class="code"><pre><code class="hljs python"><span class="hljs-keyword">from</span> tkinter <span class="hljs-keyword">import</span> *<br><br>mainwindow = Tk()<br>mainwindow.geometry(<span class="hljs-string">&quot;300x300&quot;</span>)<br>mainwindow.title(<span class="hljs-string">&quot;Hello World&quot;</span>)<br><br>lb1 = Label(text=<span class="hljs-string">&quot;Hello World! 你好世界！&quot;</span>, fore=<span class="hljs-string">&#x27;green&#x27;</span>)<br>btn1 = Button(text=<span class="hljs-string">&quot;ClickMe&quot;</span>, fore=<span class="hljs-string">&#x27;red&#x27;</span>, cursor=<span class="hljs-string">&quot;hand2&quot;</span>)<br><br>lb1.pack()<br>btn1.pack()<br><br>mainwindow.mainloop()<br></code></pre></td></tr></table></figure><p><strong>我们可以在写完控件后将其赋值，再布局</strong></p><p>也可以不赋值，如同下面这么写</p><figure class="highlight python"><table><tr><td class="gutter"><pre><span class="line">1</span><br></pre></td><td class="code"><pre><code class="hljs python">Label(text=<span class="hljs-string">&quot;Hello World! 你好世界！&quot;</span>, fore=<span class="hljs-string">&#x27;green&#x27;</span>).pack()<br></code></pre></td></tr></table></figure><p><strong>“pack”是一种布局方式，在不传入参数的情况下，会以默认形式从上到下排版</strong></p><p><strong>在Tkinter中，控件必须写出布局方式，不然控件将不会出现在窗体</strong></p><hr><p>以下是pack的一些参数</p><figure class="highlight python"><table><tr><td class="gutter"><pre><span class="line">1</span><br><span class="line">2</span><br><span class="line">3</span><br><span class="line">4</span><br><span class="line">5</span><br><span class="line">6</span><br><span class="line">7</span><br><span class="line">8</span><br><span class="line">9</span><br><span class="line">10</span><br><span class="line">11</span><br><span class="line">12</span><br><span class="line">13</span><br><span class="line">14</span><br><span class="line">15</span><br><span class="line">16</span><br><span class="line">17</span><br><span class="line">18</span><br><span class="line">19</span><br><span class="line">20</span><br><span class="line">21</span><br><span class="line">22</span><br><span class="line">23</span><br><span class="line">24</span><br><span class="line">25</span><br><span class="line">26</span><br><span class="line">27</span><br><span class="line">28</span><br><span class="line">29</span><br><span class="line">30</span><br><span class="line">31</span><br><span class="line">32</span><br><span class="line">33</span><br><span class="line">34</span><br><span class="line">35</span><br><span class="line">36</span><br><span class="line">37</span><br><span class="line">38</span><br><span class="line">39</span><br><span class="line">40</span><br><span class="line">41</span><br><span class="line">42</span><br><span class="line">43</span><br><span class="line">44</span><br><span class="line">45</span><br></pre></td><td class="code"><pre><code class="hljs python">side:按扭停靠在窗口的哪个位置<br><br>　　　　left: 左<br><br>　　　　top: 上<br><br>　　　　right: 右<br><br>　　　　botton: 下<br><br>　　fill:填充<br><br>　　　　x:水平方向填充<br><br>　　　　y:竖直方向填充<br><br>　　　　both:水平和竖直方向填充<br><br>　　　　none:不填充<br><br>　　expand:<br><br>　　　　yes:扩展整个空白区<br><br>　　　　no:不扩展<br><br>　　anchor:<br><br>　　　　N:北  下<br><br>　　　　E:东  右<br><br>　　　　S:南 下<br><br>　　　　W:西 左<br><br>　　　　CENTER:中间<br><br>　　padx:x方向的外边距<br><br>　　pady:y方向的外边距<br><br>　　ipadx:x方向的内边距<br><br>　　ipady：y方向的内边距<br></code></pre></td></tr></table></figure><p>除了pack以外，还有grid和place两种布局方法，现在无需太过意了解pack，我们在后面会讲到后两种布局方式。</p><hr><p>下面来讲控件属性</p><figure class="highlight python"><table><tr><td class="gutter"><pre><span class="line">1</span><br></pre></td><td class="code"><pre><code class="hljs python">text=<span class="hljs-string">&quot;Hello World! 你好世界！&quot;</span>, fore=<span class="hljs-string">&#x27;green&#x27;</span> <br></code></pre></td></tr></table></figure><p>在控件后的括号内，我们可以编写控件的属性，声明一个控件属性的语法如下</p><figure class="highlight python"><table><tr><td class="gutter"><pre><span class="line">1</span><br></pre></td><td class="code"><pre><code class="hljs python">xxx=<span class="hljs-string">&quot;&quot;</span>, yyy=<span class="hljs-string">&quot;&quot;</span><br></code></pre></td></tr></table></figure><p>前段写属性名称，后段写属性的值，中间用=号来赋值。在写下一个属性的时候，中间要用逗号隔开，然后再写下一个属性</p><hr><p><strong>Tkinter中内置了许许多多的控件及控件属性，由于时间（偷懒）问题不在此编写</strong></p><p><strong>但我找到了一篇讲的很好的介绍Tkinter控件及属性的文章，大家可以去👀👇</strong></p><p><a href="https://blog.csdn.net/weixin_43533825/article/details/88658691">https://blog.csdn.net/weixin_43533825/article/details/88658691</a></p><h2 id="1-3-事件处理"><a href="#1-3-事件处理" class="headerlink" title="1.3 事件处理"></a>1.3 事件处理</h2><figure class="highlight python"><table><tr><td class="gutter"><pre><span class="line">1</span><br><span class="line">2</span><br><span class="line">3</span><br><span class="line">4</span><br><span class="line">5</span><br><span class="line">6</span><br><span class="line">7</span><br><span class="line">8</span><br><span class="line">9</span><br><span class="line">10</span><br><span class="line">11</span><br><span class="line">12</span><br><span class="line">13</span><br><span class="line">14</span><br><span class="line">15</span><br><span class="line">16</span><br><span class="line">17</span><br></pre></td><td class="code"><pre><code class="hljs python"><span class="hljs-keyword">from</span> tkinter <span class="hljs-keyword">import</span> *<br><span class="hljs-keyword">from</span> tkinter <span class="hljs-keyword">import</span> messagebox<br><br>mainwindow = Tk()<br>mainwindow.geometry(<span class="hljs-string">&quot;300x300&quot;</span>)<br>mainwindow.title(<span class="hljs-string">&quot;Hello World&quot;</span>)<br><br><span class="hljs-function"><span class="hljs-keyword">def</span> <span class="hljs-title">btn1_Click</span>():</span><br>    hello = messagebox.showinfo(title=<span class="hljs-string">&quot;Hello World&quot;</span>, message=<span class="hljs-string">&quot;你好世界&quot;</span>)<br><br>lb1 = Label(text=<span class="hljs-string">&quot;Hello World! 你好世界！&quot;</span>, fore=<span class="hljs-string">&#x27;green&#x27;</span>)<br>btn1 = Button(text=<span class="hljs-string">&quot;ClickMe&quot;</span>, fore=<span class="hljs-string">&#x27;red&#x27;</span>, command=btn1_Click, cursor=<span class="hljs-string">&quot;hand2&quot;</span>)<br><br>lb1.place(x=<span class="hljs-number">5</span>, y=<span class="hljs-number">5</span>)<br>btn1.place(x=<span class="hljs-number">5</span>, y=<span class="hljs-number">28</span>)<br><br>mainwindow.mainloop()<br></code></pre></td></tr></table></figure><p>将此段编译一下，点击按钮，你会得到一个内容为“你好世界”的信息框，那这是怎么实现的呢？</p><p>这就是我们在这里要讲的：“事件处理”</p><hr><p>在Tkinter中，绑定事件是一件很容易的事</p><p><strong>我们在控件的属性中使用 command 来绑定一个事件</strong></p><figure class="highlight python"><table><tr><td class="gutter"><pre><span class="line">1</span><br></pre></td><td class="code"><pre><code class="hljs python">Button(text=<span class="hljs-string">&quot;Hello&quot;</span>, command=xxx)<br></code></pre></td></tr></table></figure><p><strong>后面则加上事件名称，事件则就是一个 def 函数，如果你用心观察，也许你也发现了示例代码中的 btn_click 事件。</strong></p><figure class="highlight python"><table><tr><td class="gutter"><pre><span class="line">1</span><br><span class="line">2</span><br><span class="line">3</span><br><span class="line">4</span><br><span class="line">5</span><br><span class="line">6</span><br><span class="line">7</span><br><span class="line">8</span><br><span class="line">9</span><br><span class="line">10</span><br><span class="line">11</span><br><span class="line">12</span><br><span class="line">13</span><br><span class="line">14</span><br><span class="line">15</span><br></pre></td><td class="code"><pre><code class="hljs python"><span class="hljs-comment"># 例子</span><br><span class="hljs-keyword">from</span> tkinter <span class="hljs-keyword">import</span> *<br><br>mainwindow = Tk();<br>mainwindow.title(<span class="hljs-string">&#x27;事件&#x27;</span>)<br>mainwindow.geometry(<span class="hljs-string">&#x27;300x300&#x27;</span>)<br><br><span class="hljs-function"><span class="hljs-keyword">def</span> <span class="hljs-title">btn1_click</span>():</span><br>    Label(text=<span class="hljs-string">&#x27;嘿，你点了我！&#x27;</span>).place(x=<span class="hljs-number">50</span>, y=<span class="hljs-number">50</span>)<br><br>btn1 = Button(text=<span class="hljs-string">&#x27;点击我&#x27;</span>, command=btn1_click, height=<span class="hljs-number">1</span>, width=<span class="hljs-number">12</span>)<br><br>btn1.place(x=<span class="hljs-number">0</span>, y=<span class="hljs-number">0</span>)<br><br>mainwindow.mainloop()<br></code></pre></td></tr></table></figure><p>这里可能有人要问了，那么上面那个信息框是怎么实现的？</p><p>这些则是使用messagebox实现的</p><p><strong>messagebox是tkinter中可以用来显示信息、确认信息的一个模块</strong></p><p><strong>messagebox有着许多参数，在此不加赘述，可见下方链接 ↓</strong></p><p><a href="https://blog.csdn.net/Bugest/article/details/81557112">https://blog.csdn.net/Bugest/article/details/81557112</a></p><p>下面是示例</p><figure class="highlight python"><table><tr><td class="gutter"><pre><span class="line">1</span><br><span class="line">2</span><br><span class="line">3</span><br><span class="line">4</span><br><span class="line">5</span><br><span class="line">6</span><br><span class="line">7</span><br><span class="line">8</span><br><span class="line">9</span><br><span class="line">10</span><br><span class="line">11</span><br><span class="line">12</span><br><span class="line">13</span><br><span class="line">14</span><br><span class="line">15</span><br><span class="line">16</span><br></pre></td><td class="code"><pre><code class="hljs python"><span class="hljs-keyword">from</span> tkinter <span class="hljs-keyword">import</span> *<br><span class="hljs-keyword">from</span> tkinter <span class="hljs-keyword">import</span> messagebox <span class="hljs-comment"># 使用messagebox需先引用</span><br><br>mainwindow = Tk();<br>mainwindow.title(<span class="hljs-string">&#x27;事件&#x27;</span>)<br>mainwindow.geometry(<span class="hljs-string">&#x27;300x300&#x27;</span>) <span class="hljs-comment"># 窗体大小</span><br><br><span class="hljs-function"><span class="hljs-keyword">def</span> <span class="hljs-title">btn1_click</span>():</span>  <br>    messagebox.showwarning(title=<span class="hljs-string">&#x27;WARNING&#x27;</span>, message=<span class="hljs-string">&#x27;警告，电脑将在30秒后爆炸&#x27;</span>)<br>    <span class="hljs-comment"># 输出一个警告窗体，其中 title= 后写窗体标题， message= 后写信息</span><br><br>btn1 = Button(text=<span class="hljs-string">&#x27;点击我&#x27;</span>, command=btn1_click) <span class="hljs-comment"># 放置按钮，绑定事件</span><br><br>btn1.place(x=<span class="hljs-number">3</span>, y=<span class="hljs-number">3</span>) <span class="hljs-comment"># 布局</span><br><br>mainwindow.mainloop()<br></code></pre></td></tr></table></figure><h2 id="1-4-总结"><a href="#1-4-总结" class="headerlink" title="1.4 总结"></a>1.4 总结</h2><p>此文为快速入门，虽是快速入门，其实Tkinter本来就是这么简单，虽然它可能比不上目前流行的一些GUI框架或是Python的GUI框架，但不可不说Tkinter也是个不错的选择。</p><p>在你看完了这篇文章后，相信你对Tkinter已经有了一定的认识，能做出自己的程序了，如果你还希望进一步学习Tkinter，这里有几份推荐给你</p><hr><p>#Tkinter详细教程#  <a href="https://blog.csdn.net/RNG_uzi_/article/details/89792518?ops_request_misc=%7B%22request_id%22:%22163577762916780255274290%22,%22scm%22:%2220140713.130102334..%22%7D&request_id=163577762916780255274290&biz_id=0&utm_medium=distribute.pc_search_result.none-task-blog-2~all~top_positive~default-1-89792518.first_rank_v2_pc_rank_v29&utm_term=tkinter">Python-Tkinter图形化界面设计（详细教程 ）_Zhangfei Wang-CSDN博客_tkinter</a> </p><blockquote><p><strong>u1s1，这个比我讲得详细多了</strong></p></blockquote><p>#Tkinter的place布局#  <a href="https://blog.csdn.net/Riven_h/article/details/117531522?ops_request_misc=%7B%22request_id%22:%22163577762916780255249776%22,%22scm%22:%2220140713.130102334.pc_blog.%22%7D&request_id=163577762916780255249776&biz_id=0&utm_medium=distribute.pc_search_result.none-task-blog-2~all~first_rank_ecpm_v1~rank_v31_ecpm-8-117531522.first_rank_v2_pc_rank_v29&utm_term=tkinter">tkinter的Frame布局_Riven_h的博客-CSDN博客</a></p><blockquote><p><strong>Tkinter的Place布局方法</strong></p></blockquote><p>#Tkinter的grid布局#  <a href="https://blog.csdn.net/weixin_43708622/article/details/107134216?ops_request_misc=%7B%22request_id%22:%22163577762916780255249776%22,%22scm%22:%2220140713.130102334.pc_blog.%22%7D&request_id=163577762916780255249776&biz_id=0&utm_medium=distribute.pc_search_result.none-task-blog-2~all~first_rank_ecpm_v1~rank_v31_ecpm-17-107134216.first_rank_v2_pc_rank_v29&utm_term=tkinter">tkinter-grid布局详解_渔道的博客-CSDN博客</a></p><blockquote><p><strong>Tkinter的Grid布局方法</strong></p></blockquote><p>#Tkinter窗体设置#  <a href="https://blog.csdn.net/m0_51713294/article/details/110529034?ops_request_misc=&request_id=&biz_id=102&utm_term=python">怎么用python tkinter做窗口边框美化？_m0_51713294的博客-CSDN博客</a></p><blockquote><p><strong>关于Tkinter窗体的一些设置，挺实用的</strong></p></blockquote><p>#Tkinter学生管理系统#  <a href="https://blog.csdn.net/qq1123642601/article/details/90760485?ops_request_misc=%7B%22request_id%22:%22163577913716780261963745%22,%22scm%22:%2220140713.130102334..%22%7D&request_id=163577913716780261963745&biz_id=0&utm_medium=distribute.pc_search_result.none-task-blog-2~all~sobaiduend~default-1-90760485.first_rank_v2_pc_rank_v29&utm_term=python+tkinter%E7%AE%A1%E7%90%86%E7%B3%BB%E7%BB%9F&spm=1018.2226.3001.4187">python+tkinter学生管理系统_WF帆少的博客-CSDN博客_tkinter学生管理系统</a></p><blockquote><p><strong>Tkinter一个做学生管理系统的小例子</strong></p></blockquote><p>#Tkinter五子棋#  <a href="https://blog.csdn.net/qq_40298768/article/details/106082306?ops_request_misc=%7B%22request_id%22:%22163577913816780261938236%22,%22scm%22:%2220140713.130102334.pc_all.%22%7D&request_id=163577913816780261938236&biz_id=0&utm_medium=distribute.pc_search_result.none-task-blog-2~all~first_rank_ecpm_v1~rank_v31_ecpm-6-106082306.first_rank_v2_pc_rank_v29&utm_term=python+tkinter%E5%81%9A%E6%B8%B8%E6%88%8F">Python tkinter实现小游戏五子棋_guocy-ww的博客-CSDN博客</a></p><blockquote><p><strong>Tkinter五子棋</strong></p></blockquote><p>The End.</p><p><em><strong>人生充满了起起落落。关键在于，在顶端时好好享受；在低谷时不失勇气。</strong></em> -《海贼王》</p>]]></content>
    
    
    <categories>
      
      <category>CODE</category>
      
    </categories>
    
    
    <tags>
      
      <tag>教程</tag>
      
    </tags>
    
  </entry>
  
  
  
  <entry>
    <title>Hello World</title>
    <link href="/2021/10/30/hello-world/"/>
    <url>/2021/10/30/hello-world/</url>
    
    <content type="html"><![CDATA[<h1 id="Hello-World"><a href="#Hello-World" class="headerlink" title="Hello World"></a><strong>Hello World</strong></h1><h2 id="1-C"><a href="#1-C" class="headerlink" title="1. C"></a>1. C</h2><figure class="highlight c"><table><tr><td class="gutter"><pre><span class="line">1</span><br><span class="line">2</span><br><span class="line">3</span><br><span class="line">4</span><br><span class="line">5</span><br><span class="line">6</span><br><span class="line">7</span><br></pre></td><td class="code"><pre><code class="hljs c"><span class="hljs-meta">#<span class="hljs-meta-keyword">include</span> </span><br> <br><span class="hljs-function"><span class="hljs-keyword">int</span> <span class="hljs-title">main</span><span class="hljs-params">()</span></span><br><span class="hljs-function"></span>&#123;<br>    <span class="hljs-built_in">printf</span>(<span class="hljs-string">&quot;Hello, World&quot;</span>);<br>    <span class="hljs-keyword">return</span>(<span class="hljs-number">0</span>);<br>&#125;<br></code></pre></td></tr></table></figure><hr><h2 id="2-C"><a href="#2-C" class="headerlink" title="2. C++"></a>2. C++</h2><figure class="highlight c++"><table><tr><td class="gutter"><pre><span class="line">1</span><br><span class="line">2</span><br><span class="line">3</span><br><span class="line">4</span><br><span class="line">5</span><br><span class="line">6</span><br><span class="line">7</span><br></pre></td><td class="code"><pre><code class="hljs c++"><span class="hljs-meta">#<span class="hljs-meta-keyword">include</span> </span><br> <br><span class="hljs-function"><span class="hljs-keyword">int</span> <span class="hljs-title">main</span><span class="hljs-params">()</span></span><br><span class="hljs-function"></span>&#123;<br>    std::cout &lt;&lt; <span class="hljs-string">&quot;Hello World&quot;</span>;<br>    <span class="hljs-keyword">return</span> <span class="hljs-number">0</span>;<br>&#125;<br></code></pre></td></tr></table></figure><hr><h2 id="3-C"><a href="#3-C" class="headerlink" title="3. C#"></a>3. C#</h2><figure class="highlight csharp"><table><tr><td class="gutter"><pre><span class="line">1</span><br><span class="line">2</span><br><span class="line">3</span><br><span class="line">4</span><br><span class="line">5</span><br><span class="line">6</span><br><span class="line">7</span><br><span class="line">8</span><br></pre></td><td class="code"><pre><code class="hljs csharp"><span class="hljs-keyword">using</span> System;<br><span class="hljs-keyword">class</span> <span class="hljs-title">Program</span><br>&#123;<br>    <span class="hljs-function"><span class="hljs-keyword">public</span> <span class="hljs-keyword">static</span> <span class="hljs-keyword">void</span> <span class="hljs-title">Main</span>(<span class="hljs-params"><span class="hljs-built_in">string</span>[] args</span>)</span><br>    &#123;<br>        Console.WriteLine(<span class="hljs-string">&quot;Hello, World&quot;</span>);<br>    &#125;<br>&#125;<br></code></pre></td></tr></table></figure><hr><h2 id="4-Bash"><a href="#4-Bash" class="headerlink" title="4. Bash"></a>4. Bash</h2><figure class="highlight bash"><table><tr><td class="gutter"><pre><span class="line">1</span><br></pre></td><td class="code"><pre><code class="hljs bash"><span class="hljs-built_in">echo</span> <span class="hljs-string">&quot;Hello, World&quot;</span><br></code></pre></td></tr></table></figure><hr><h2 id="5-Basic"><a href="#5-Basic" class="headerlink" title="5. Basic"></a>5. Basic</h2><figure class="highlight basic"><table><tr><td class="gutter"><pre><span class="line">1</span><br></pre></td><td class="code"><pre><code class="hljs basic"><span class="hljs-keyword">PRINT</span> <span class="hljs-string">&quot;Hello, World&quot;</span><br></code></pre></td></tr></table></figure><hr><h2 id="6-HTML"><a href="#6-HTML" class="headerlink" title="6. HTML"></a>6. HTML</h2><figure class="highlight html"><table><tr><td class="gutter"><pre><span class="line">1</span><br></pre></td><td class="code"><pre><code class="hljs html"><span class="hljs-tag">&lt;<span class="hljs-name">h1</span>&gt;</span>Hello World!<span class="hljs-tag">&lt;/<span class="hljs-name">h1</span>&gt;</span><br></code></pre></td></tr></table></figure><hr><h2 id="7-Java"><a href="#7-Java" class="headerlink" title="7. Java"></a>7. Java</h2><figure class="highlight java"><table><tr><td class="gutter"><pre><span class="line">1</span><br><span class="line">2</span><br><span class="line">3</span><br><span class="line">4</span><br><span class="line">5</span><br></pre></td><td class="code"><pre><code class="hljs java"><span class="hljs-keyword">public</span> <span class="hljs-class"><span class="hljs-keyword">class</span> <span class="hljs-title">Main</span> </span>&#123;<br>    <span class="hljs-function"><span class="hljs-keyword">public</span> <span class="hljs-keyword">static</span> <span class="hljs-keyword">void</span> <span class="hljs-title">main</span><span class="hljs-params">(String[] args)</span> </span>&#123;<br>        System.out.println(<span class="hljs-string">&quot;Hello, World!&quot;</span>);<br>    &#125;<br>&#125;<br></code></pre></td></tr></table></figure><hr><h2 id="8-Clipper"><a href="#8-Clipper" class="headerlink" title="8. Clipper"></a>8. Clipper</h2><figure class="highlight 1c"><table><tr><td class="gutter"><pre><span class="line">1</span><br></pre></td><td class="code"><pre><code class="hljs 1c">? <span class="hljs-string">&quot;Hello, World&quot;</span><br></code></pre></td></tr></table></figure><hr><h2 id="9-Delphi"><a href="#9-Delphi" class="headerlink" title="9. Delphi"></a>9. Delphi</h2><figure class="highlight java"><table><tr><td class="gutter"><pre><span class="line">1</span><br><span class="line">2</span><br><span class="line">3</span><br><span class="line">4</span><br></pre></td><td class="code"><pre><code class="hljs java">program HelloWorld;<br><span class="hljs-function">begin</span><br><span class="hljs-function">  <span class="hljs-title">Writeln</span><span class="hljs-params">(<span class="hljs-string">&#x27;Hello, World&#x27;</span>)</span></span>;<br>end.<br></code></pre></td></tr></table></figure><hr><h2 id="10-CoffeeScript"><a href="#10-CoffeeScript" class="headerlink" title="10. CoffeeScript"></a>10. CoffeeScript</h2><figure class="highlight coffeescript"><table><tr><td class="gutter"><pre><span class="line">1</span><br></pre></td><td class="code"><pre><code class="hljs coffeescript"><span class="hljs-built_in">console</span>.log <span class="hljs-string">&#x27;Hello, World&#x27;</span><br></code></pre></td></tr></table></figure><hr><h2 id="11-MatLab"><a href="#11-MatLab" class="headerlink" title="11. MatLab"></a>11. MatLab</h2><figure class="highlight matlab"><table><tr><td class="gutter"><pre><span class="line">1</span><br></pre></td><td class="code"><pre><code class="hljs matlab"><span class="hljs-built_in">disp</span>(<span class="hljs-string">&#x27;Hello, World&#x27;</span>)<br></code></pre></td></tr></table></figure><hr><h2 id="12-Julia"><a href="#12-Julia" class="headerlink" title="12. Julia"></a>12. Julia</h2><figure class="highlight julia"><table><tr><td class="gutter"><pre><span class="line">1</span><br></pre></td><td class="code"><pre><code class="hljs julia">println(<span class="hljs-string">&quot;Hello, World&quot;</span>)<br></code></pre></td></tr></table></figure><hr><h2 id="13-JavaScript"><a href="#13-JavaScript" class="headerlink" title="13. JavaScript"></a>13. JavaScript</h2><figure class="highlight js"><table><tr><td class="gutter"><pre><span class="line">1</span><br></pre></td><td class="code"><pre><code class="hljs js"><span class="hljs-built_in">document</span>.write(<span class="hljs-string">&#x27;Hello, World&#x27;</span>);<br></code></pre></td></tr></table></figure><hr><h2 id="14-Logo"><a href="#14-Logo" class="headerlink" title="14. Logo"></a>14. Logo</h2><figure class="highlight cpp"><table><tr><td class="gutter"><pre><span class="line">1</span><br></pre></td><td class="code"><pre><code class="hljs cpp">print [Hello, World]<br></code></pre></td></tr></table></figure><hr><h2 id="15-jQuery"><a href="#15-jQuery" class="headerlink" title="15. jQuery"></a>15. jQuery</h2><figure class="highlight js"><table><tr><td class="gutter"><pre><span class="line">1</span><br></pre></td><td class="code"><pre><code class="hljs js">$(<span class="hljs-string">&quot;body&quot;</span>).append(<span class="hljs-string">&quot;Hello, World&quot;</span>);<br></code></pre></td></tr></table></figure><hr><h2 id="16-Perl-5"><a href="#16-Perl-5" class="headerlink" title="16. Perl 5"></a>16. Perl 5</h2><figure class="highlight perl"><table><tr><td class="gutter"><pre><span class="line">1</span><br></pre></td><td class="code"><pre><code class="hljs perl"><span class="hljs-keyword">print</span> <span class="hljs-string">&quot;Hello, World&quot;</span>;<br></code></pre></td></tr></table></figure><hr><h2 id="17-Pascal"><a href="#17-Pascal" class="headerlink" title="17. Pascal"></a>17. Pascal</h2><figure class="highlight pascal"><table><tr><td class="gutter"><pre><span class="line">1</span><br><span class="line">2</span><br><span class="line">3</span><br><span class="line">4</span><br></pre></td><td class="code"><pre><code class="hljs pascal"><span class="hljs-keyword">program</span> HelloWorld;<br><span class="hljs-keyword">begin</span><br>  WriteLn(<span class="hljs-string">&#x27;Hello, World&#x27;</span>);<br><span class="hljs-keyword">end</span>.<br></code></pre></td></tr></table></figure><hr><h2 id="18-Objective-C"><a href="#18-Objective-C" class="headerlink" title="18. Objective-C"></a>18. Objective-C</h2><figure class="highlight plaintext"><table><tr><td class="gutter"><pre><span class="line">1</span><br><span class="line">2</span><br><span class="line">3</span><br><span class="line">4</span><br><span class="line">5</span><br><span class="line">6</span><br><span class="line">7</span><br><span class="line">8</span><br></pre></td><td class="code"><pre><code class="hljs objective-c">#import <br>#import <br> <br>int main(void)<br>&#123;<br>    NSLog(@&quot;Hello, World&quot;);<br>    return 0;<br>&#125;<br></code></pre></td></tr></table></figure><hr><h2 id="19-Visual-Basic-NET"><a href="#19-Visual-Basic-NET" class="headerlink" title="19. Visual Basic .NET"></a>19. Visual Basic .NET</h2><figure class="highlight plaintext"><figcaption><span>basic</span></figcaption><table><tr><td class="gutter"><pre><span class="line">1</span><br><span class="line">2</span><br><span class="line">3</span><br><span class="line">4</span><br><span class="line">5</span><br></pre></td><td class="code"><pre><code class="hljs visual">Module Module1<br>    Sub Main()<br>        Console.WriteLine(&quot;Hello, World&quot;)<br>    End Sub<br>End Module<br></code></pre></td></tr></table></figure><hr><h2 id="20-R"><a href="#20-R" class="headerlink" title="20. R"></a>20. R</h2><figure class="highlight r"><table><tr><td class="gutter"><pre><span class="line">1</span><br></pre></td><td class="code"><pre><code class="hljs R">cat(<span class="hljs-string">&#x27;Hello, World&#x27;</span>)<br></code></pre></td></tr></table></figure><hr><h2 id="21-VBScript"><a href="#21-VBScript" class="headerlink" title="21. VBScript"></a>21. VBScript</h2><figure class="highlight vbscript"><table><tr><td class="gutter"><pre><span class="line">1</span><br></pre></td><td class="code"><pre><code class="hljs vbscript">MsgBox <span class="hljs-string">&quot;Hello, World&quot;</span><br></code></pre></td></tr></table></figure><hr><h2 id="22-XSLT"><a href="#22-XSLT" class="headerlink" title="22. XSLT"></a>22. XSLT</h2><figure class="highlight autohotkey"><table><tr><td class="gutter"><pre><span class="line">1</span><br></pre></td><td class="code"><pre><code class="hljs autohotkey"><span class="hljs-built_in">Hello,</span> World<br></code></pre></td></tr></table></figure><hr><h2 id="23-Processing"><a href="#23-Processing" class="headerlink" title="23. Processing"></a>23. Processing</h2><figure class="highlight c++"><table><tr><td class="gutter"><pre><span class="line">1</span><br><span class="line">2</span><br><span class="line">3</span><br></pre></td><td class="code"><pre><code class="hljs c++"><span class="hljs-function"><span class="hljs-keyword">void</span> <span class="hljs-title">setup</span><span class="hljs-params">()</span></span>&#123;<br>  <span class="hljs-built_in">println</span>(<span class="hljs-string">&quot;Hello, World&quot;</span>);<br>&#125;<br></code></pre></td></tr></table></figure><hr><h2 id="24-Ruby"><a href="#24-Ruby" class="headerlink" title="24. Ruby"></a>24. Ruby</h2><figure class="highlight ruby"><table><tr><td class="gutter"><pre><span class="line">1</span><br></pre></td><td class="code"><pre><code class="hljs ruby">puts <span class="hljs-string">&quot;Hello, World&quot;</span><br></code></pre></td></tr></table></figure><hr><h2 id="25-Swift"><a href="#25-Swift" class="headerlink" title="25. Swift"></a>25. Swift</h2><figure class="highlight swift"><table><tr><td class="gutter"><pre><span class="line">1</span><br></pre></td><td class="code"><pre><code class="hljs swift"><span class="hljs-built_in">print</span>(<span class="hljs-string">&quot;Hello, World&quot;</span>)<br></code></pre></td></tr></table></figure><hr><h2 id="26-Python"><a href="#26-Python" class="headerlink" title="26. Python"></a>26. Python</h2><figure class="highlight python"><table><tr><td class="gutter"><pre><span class="line">1</span><br></pre></td><td class="code"><pre><code class="hljs python"><span class="hljs-built_in">print</span> (<span class="hljs-string">&quot;Hello, World&quot;</span>)<br></code></pre></td></tr></table></figure>]]></content>
    
    
    <categories>
      
      <category>CODE</category>
      
    </categories>
    
    
    <tags>
      
      <tag>Hello World</tag>
      
    </tags>
    
  </entry>
  
  
  
  
</search>
